myaml/__init__.py
myaml/myaml.py
myaml-1.0.1.dist-info/LICENSE
myaml-1.0.1.dist-info/METADATA
myaml-1.0.1.dist-info/WHEEL
myaml-1.0.1.dist-info/top_level.txt
myaml-1.0.1.dist-info/RECORD
