Metadata-Version: 2.1
Name: myaml
Version: 1.0.1
Summary: M(ath)YAML: evaluate math expressions in YAML files.
Home-page: https://github.com/alexandru-dinu/myaml
Author: Alexandru Dinu
Author-email: alex.dinu07@gmail.com
License: Apache 2.0
Platform: UNKNOWN
Classifier: Programming Language :: Python :: 3
Classifier: Topic :: Scientific/Engineering
Requires-Dist: PyYAML
Requires-Dist: sympy
